{
    "name": "Sun",
    "description": "Black and White sun background.",
    "authors": [
        {
            "name": "Artan",
            "id": "0"
        }
  ],
  "semanticColors": {
    "BACKGROUND_MODIFIER_ACTIVE": [
      "#DA4453"
    ],
    "CHANNEL_ICON": [
      "#DA4453"
    ],
    "INTERACTIVE_ACTIVE": [
      "#DA4453"
    ],
    "BG_BASE_SECONDARY": [
      "#DA4453"
    ],
    "INTERACTIVE_NORMAL": [
      "#DA4453"
    ],
    "REDESIGN_BUTTON_SECONDARY_BORDER": [
      "#DA4453"
    ],
    "REDESIGN_CHANNEL_CATEGORY_NAME_TEXT": [
      "#DA4453"
    ],
    "TEXT_MUTED": [
      "#DA4453"
    ],
    "TEXT_PRIMARY": [
      "#DA4453"
    ],
    "TEXT_SECONDARY": [
      "#DA4453"
    ],
    "REDESIGN_INPUT_CONTROL_SELECTED": [
      "#DA4453"
    ],
    "BG_BRAND": [
      "#DA4453"
    ]
},
   "background":{
      "url":"https://raw.githubusercontent.com/Bratan14/Bratans-Enmity-Themes/main/backgrounds/IMG_3239.png",
      "alpha":0.7
   }
}
